latex_to_zh/__init__.py
latex_to_zh/g4/Latex.interp
latex_to_zh/g4/Latex.tokens
latex_to_zh/g4/LatexLexer.interp
latex_to_zh/g4/LatexLexer.py
latex_to_zh/g4/LatexLexer.tokens
latex_to_zh/g4/LatexListener.py
latex_to_zh/g4/LatexParser.py
latex_to_zh/g4/LatexVisitor.py
latex_to_zh/latex_to_zh.py
latex_to_zh-0.1.1.dist-info/METADATA
latex_to_zh-0.1.1.dist-info/WHEEL
latex_to_zh-0.1.1.dist-info/RECORD
